{
  "Title": "Typewriter",
  "Description": "Mechanical device for typing characters",
  "Paragraph": "A typewriter is a mechanical or electromechanical machine for typing characters. Typically, a typewriter has an array of keys, and each one causes a different single character to be produced on paper by striking an inked ribbon selectively against the paper with a type element. Thereby, the machine produces a legible written document composed of ink and paper. By the end of the 19th century, a person who used such a device was also referred to as a typewriter.",
  "Tags": [
    "tool",
    "language"
  ],
  "image": "images\\Typewriter.jpg"
}